<?xml version = '1.0' encoding = 'UTF-8'?>
<FKIndexAssociation class="oracle.dbtools.crest.model.design.relational.FKIndexAssociation" directorySegmentName="seg_0" id="0FA64341-5C7F-6813-060C-3B22B3B6D85E" containerWithKeyObject="5A17409F-C75C-3785-22F5-850F1B647BA7" localFKIndex="0A04B0B2-7D21-7726-309E-2A5C0EAF147F" name="SYS_C008937">
<sourceConnName>BD1</sourceConnName>
<sourceObjSchema>SYSTEM</sourceObjSchema>
<sourceObjName>SYS_C008937</sourceObjName>
<createdBy>Namikaze</createdBy>
<createdTime>2023-11-11 00:46:55 UTC</createdTime>
<ownerDesignName>Diagrama ER object</ownerDesignName>
<referredTableLongName>SYSTEM.USUARIO</referredTableLongName>
<deleteRule>NO ACTION</deleteRule>
<referredTableID>89B6FD56-C100-2DEC-9AD1-3B3D0B0696C0</referredTableID>
<keyObject>EECCD3B6-F2CF-0CF3-A010-6D49058FB343</keyObject>
<referredKeyID>EECCD3B6-F2CF-0CF3-A010-6D49058FB343</referredKeyID>
<mandatory>false</mandatory>
<refColNames>ID_USUARIO</refColNames>
<transferable>true</transferable>
<rely>false</rely>
<columnDependencyConstraintGenerateInDDL>true</columnDependencyConstraintGenerateInDDL>
</FKIndexAssociation>